tibia/__init__.py
tibia/future.py
tibia/future_maybe.py
tibia/future_result.py
tibia/iterable/__init__.py
tibia/iterable/aio.py
tibia/iterable/eager.py
tibia/iterable/lazy.py
tibia/iterable/threaded.py
tibia/mapping/__init__.py
tibia/mapping/item.py
tibia/mapping/key.py
tibia/mapping/value.py
tibia/maybe.py
tibia/predicate.py
tibia/py.typed
tibia/result.py
tibia/utils.py
tibia/value.py
tibia-2.3.1.dist-info/LICENCE
tibia-2.3.1.dist-info/METADATA
tibia-2.3.1.dist-info/WHEEL
tibia-2.3.1.dist-info/RECORD
