Metadata-Version: 2.3
Name: tibia
Version: 2.3.1
Summary: Monads in python for pipeline-based development with Rust-like interface
License: MIT
Keywords: monad,functional,pipeline,rust
Author: Ilya Katun
Author-email: katun.ilya@gmail.com
Requires-Python: >=3.12,<4.0
Classifier: License :: OSI Approved :: MIT License
Classifier: Programming Language :: Python :: 3
Classifier: Programming Language :: Python :: 3.12
Classifier: Programming Language :: Python :: 3.13
Project-URL: Repository, https://github.com/katunilya/tibia
